{
  "updated": "2026-05-21T11:56:25.742Z",
  "overview": {
    "totalSectorIn": 35665564752,
    "totalSectorOut": 0,
    "netFlow": 35665564752,
    "sectorCount": 30,
    "inflowSectorCount": 30
  },
  "marketFlow": null,
  "northBound": null,
  "sectors": [
    {
      "code": "BK1211",
      "name": "汽车",
      "price": 4596.26,
      "change": -1.01,
      "changeAmount": -47.06,
      "mainNetIn": 3629450240,
      "mainNetInRatio": 2.58,
      "superLargeNetIn": 4215217920,
      "superLargeNetInRatio": 3,
      "largeNetIn": -585767680,
      "mediumNetIn": -2856152064
    },
    {
      "code": "BK1335",
      "name": "面板",
      "price": 3514.02,
      "change": 0.89,
      "changeAmount": 31.15,
      "mainNetIn": 3608640768,
      "mainNetInRatio": 8.36,
      "superLargeNetIn": 4921407488,
      "superLargeNetInRatio": 11.4,
      "largeNetIn": -1312766720,
      "mediumNetIn": -2048131840
    },
    {
      "code": "BK0481",
      "name": "汽车零部件",
      "price": 52280.08,
      "change": -0.99,
      "changeAmount": -524.27,
      "mainNetIn": 3204148224,
      "mainNetInRatio": 2.74,
      "superLargeNetIn": 3779347456,
      "superLargeNetInRatio": 3.23,
      "largeNetIn": -575199232,
      "mediumNetIn": -2414887168
    },
    {
      "code": "BK1455",
      "name": "家电零部件Ⅲ",
      "price": 5795.84,
      "change": -1.89,
      "changeAmount": -111.79,
      "mainNetIn": 2097566464,
      "mainNetInRatio": 6.84,
      "superLargeNetIn": 1925234688,
      "superLargeNetInRatio": 6.28,
      "largeNetIn": 172331776,
      "mediumNetIn": -1032402432
    },
    {
      "code": "BK1242",
      "name": "家电零部件Ⅱ",
      "price": 5795.84,
      "change": -1.89,
      "changeAmount": -111.79,
      "mainNetIn": 2097566464,
      "mainNetInRatio": 6.84,
      "superLargeNetIn": 1925234688,
      "superLargeNetInRatio": 6.28,
      "largeNetIn": 172331776,
      "mediumNetIn": -1032402432
    },
    {
      "code": "BK1038",
      "name": "光学光电子",
      "price": 2315.71,
      "change": -0.69,
      "changeAmount": -16.08,
      "mainNetIn": 2039054336,
      "mainNetInRatio": 1.84,
      "superLargeNetIn": 4201636864,
      "superLargeNetInRatio": 3.79,
      "largeNetIn": -2162582528,
      "mediumNetIn": -1213006336
    },
    {
      "code": "BK0456",
      "name": "家用电器",
      "price": 25878.81,
      "change": -1.79,
      "changeAmount": -471.84,
      "mainNetIn": 1806588672,
      "mainNetInRatio": 3.59,
      "superLargeNetIn": 1430273792,
      "superLargeNetInRatio": 2.84,
      "largeNetIn": 376314880,
      "mediumNetIn": -688461824
    },
    {
      "code": "BK1526",
      "name": "底盘与发动机系统",
      "price": 4986.97,
      "change": -0.77,
      "changeAmount": -38.83,
      "mainNetIn": 1795110912,
      "mainNetInRatio": 3.18,
      "superLargeNetIn": 1833000960,
      "superLargeNetInRatio": 3.25,
      "largeNetIn": -37890048,
      "mediumNetIn": -1051787264
    },
    {
      "code": "BK1366",
      "name": "证券Ⅲ",
      "price": 137476.1,
      "change": -0.15,
      "changeAmount": -207.26,
      "mainNetIn": 1677792000,
      "mainNetInRatio": 2.82,
      "superLargeNetIn": 1153800192,
      "superLargeNetInRatio": 1.94,
      "largeNetIn": 523991808,
      "mediumNetIn": -937391616
    },
    {
      "code": "BK0473",
      "name": "证券Ⅱ",
      "price": 137476.1,
      "change": -0.15,
      "changeAmount": -207.26,
      "mainNetIn": 1677792000,
      "mainNetInRatio": 2.82,
      "superLargeNetIn": 1153800192,
      "superLargeNetInRatio": 1.94,
      "largeNetIn": 523991808,
      "mediumNetIn": -937391616
    },
    {
      "code": "BK1529",
      "name": "汽车电子电气系统",
      "price": 4392.71,
      "change": 0.17,
      "changeAmount": 7.48,
      "mainNetIn": 1262341824,
      "mainNetInRatio": 4.87,
      "superLargeNetIn": 1531393984,
      "superLargeNetInRatio": 5.9,
      "largeNetIn": -269052160,
      "mediumNetIn": -1088141824
    },
    {
      "code": "BK1408",
      "name": "机器人",
      "price": 10843.12,
      "change": 0.53,
      "changeAmount": 57.53,
      "mainNetIn": 987600784,
      "mainNetInRatio": 4.85,
      "superLargeNetIn": 809662352,
      "superLargeNetInRatio": 3.97,
      "largeNetIn": 177938432,
      "mediumNetIn": -358861312
    },
    {
      "code": "BK1519",
      "name": "电动乘用车",
      "price": 5682.53,
      "change": 2.41,
      "changeAmount": 133.53,
      "mainNetIn": 911204464,
      "mainNetInRatio": 8.99,
      "superLargeNetIn": 818886256,
      "superLargeNetInRatio": 8.08,
      "largeNetIn": 92318208,
      "mediumNetIn": -679170976
    },
    {
      "code": "BK1600",
      "name": "医疗研发外包",
      "price": 6818.67,
      "change": -0.09,
      "changeAmount": -5.9,
      "mainNetIn": 815775600,
      "mainNetInRatio": 4.58,
      "superLargeNetIn": 335074672,
      "superLargeNetInRatio": 1.88,
      "largeNetIn": 480700928,
      "mediumNetIn": -512490240
    },
    {
      "code": "BK1203",
      "name": "非银金融",
      "price": 2462.87,
      "change": -0.8,
      "changeAmount": -19.8,
      "mainNetIn": 780228352,
      "mainNetInRatio": 0.99,
      "superLargeNetIn": 485419008,
      "superLargeNetInRatio": 0.62,
      "largeNetIn": 294809344,
      "mediumNetIn": -614240768
    },
    {
      "code": "BK1611",
      "name": "国有大型银行Ⅲ",
      "price": 2989.79,
      "change": 1.02,
      "changeAmount": 30.13,
      "mainNetIn": 755558640,
      "mainNetInRatio": 8.38,
      "superLargeNetIn": -60134752,
      "superLargeNetInRatio": -0.67,
      "largeNetIn": 815693392,
      "mediumNetIn": -244881152
    },
    {
      "code": "BK1262",
      "name": "乘用车",
      "price": 4227.69,
      "change": 0.41,
      "changeAmount": 17.31,
      "mainNetIn": 734882784,
      "mainNetInRatio": 5.92,
      "superLargeNetIn": 770879152,
      "superLargeNetInRatio": 6.21,
      "largeNetIn": -35996368,
      "mediumNetIn": -631559232
    },
    {
      "code": "BK1307",
      "name": "电机Ⅲ",
      "price": 2934.36,
      "change": 0.11,
      "changeAmount": 3.21,
      "mainNetIn": 654700704,
      "mainNetInRatio": 3.78,
      "superLargeNetIn": 423210320,
      "superLargeNetInRatio": 2.45,
      "largeNetIn": 231490384,
      "mediumNetIn": -132430336
    },
    {
      "code": "BK1030",
      "name": "电机Ⅱ",
      "price": 2934.36,
      "change": 0.11,
      "changeAmount": 3.21,
      "mainNetIn": 654700704,
      "mainNetInRatio": 3.78,
      "superLargeNetIn": 423210320,
      "superLargeNetInRatio": 2.45,
      "largeNetIn": 231490384,
      "mediumNetIn": -132430336
    },
    {
      "code": "BK1605",
      "name": "医疗设备",
      "price": 6413.78,
      "change": -1.56,
      "changeAmount": -101.52,
      "mainNetIn": 589915712,
      "mainNetInRatio": 3.63,
      "superLargeNetIn": 590331200,
      "superLargeNetInRatio": 3.64,
      "largeNetIn": -415488,
      "mediumNetIn": -269222912
    },
    {
      "code": "BK1283",
      "name": "银行",
      "price": 4056.9,
      "change": 0.16,
      "changeAmount": 6.68,
      "mainNetIn": 503042560,
      "mainNetInRatio": 2.09,
      "superLargeNetIn": -412209152,
      "superLargeNetInRatio": -1.71,
      "largeNetIn": 915251712,
      "mediumNetIn": -23364864
    },
    {
      "code": "BK0475",
      "name": "银行Ⅱ",
      "price": 4056.9,
      "change": 0.16,
      "changeAmount": 6.68,
      "mainNetIn": 503042560,
      "mainNetInRatio": 2.09,
      "superLargeNetIn": -412209152,
      "superLargeNetInRatio": -1.71,
      "largeNetIn": 915251712,
      "mediumNetIn": -23364864
    },
    {
      "code": "BK1411",
      "name": "非金属材料Ⅲ",
      "price": 2112.09,
      "change": -3.26,
      "changeAmount": -71.26,
      "mainNetIn": 433399168,
      "mainNetInRatio": 6.14,
      "superLargeNetIn": 372144832,
      "superLargeNetInRatio": 5.28,
      "largeNetIn": 61254336,
      "mediumNetIn": -144152592
    },
    {
      "code": "BK1020",
      "name": "非金属材料Ⅱ",
      "price": 2112.09,
      "change": -3.26,
      "changeAmount": -71.26,
      "mainNetIn": 433399168,
      "mainNetInRatio": 6.14,
      "superLargeNetIn": 372144832,
      "superLargeNetInRatio": 5.28,
      "largeNetIn": 61254336,
      "mediumNetIn": -144152592
    },
    {
      "code": "BK0727",
      "name": "医疗服务",
      "price": 1290.32,
      "change": -1.23,
      "changeAmount": -16.07,
      "mainNetIn": 360528976,
      "mainNetInRatio": 1.4,
      "superLargeNetIn": 1012816,
      "superLargeNetInRatio": 0,
      "largeNetIn": 359516160,
      "mediumNetIn": -508737536
    },
    {
      "code": "BK1041",
      "name": "医疗器械",
      "price": 979.79,
      "change": -1.96,
      "changeAmount": -19.57,
      "mainNetIn": 359388480,
      "mainNetInRatio": 1.09,
      "superLargeNetIn": 685906752,
      "superLargeNetInRatio": 2.09,
      "largeNetIn": -326518272,
      "mediumNetIn": -461520896
    },
    {
      "code": "BK1625",
      "name": "钨",
      "price": 8041.04,
      "change": -0.44,
      "changeAmount": -35.46,
      "mainNetIn": 354950704,
      "mainNetInRatio": 3.02,
      "superLargeNetIn": 59496960,
      "superLargeNetInRatio": 0.51,
      "largeNetIn": 295453744,
      "mediumNetIn": -164608112
    },
    {
      "code": "BK1461",
      "name": "玻璃制造",
      "price": 2045.17,
      "change": 1.55,
      "changeAmount": 31.3,
      "mainNetIn": 331254928,
      "mainNetInRatio": 12.13,
      "superLargeNetIn": 292172256,
      "superLargeNetInRatio": 10.69,
      "largeNetIn": 39082672,
      "mediumNetIn": -156375008
    },
    {
      "code": "BK0546",
      "name": "玻璃玻纤",
      "price": 67041.41,
      "change": 0.04,
      "changeAmount": 25.72,
      "mainNetIn": 329330560,
      "mainNetInRatio": 1.47,
      "superLargeNetIn": 381942400,
      "superLargeNetInRatio": 1.71,
      "largeNetIn": -52611840,
      "mediumNetIn": -44821760
    },
    {
      "code": "BK1377",
      "name": "火力发电",
      "price": 2639.63,
      "change": -1.15,
      "changeAmount": -30.6,
      "mainNetIn": 276608000,
      "mainNetInRatio": 0.71,
      "superLargeNetIn": 1185731584,
      "superLargeNetInRatio": 3.02,
      "largeNetIn": -909123584,
      "mediumNetIn": -829559296
    }
  ],
  "concepts": [
    {
      "code": "BK0984",
      "name": "华为汽车",
      "change": -1.03,
      "mainNetIn": 4836068352,
      "mainNetInRatio": 5.02
    },
    {
      "code": "BK1145",
      "name": "机器人执行器",
      "change": 1.31,
      "mainNetIn": 4010487040,
      "mainNetInRatio": 5.86
    },
    {
      "code": "BK1057",
      "name": "电子纸概念",
      "change": 0.52,
      "mainNetIn": 2723481088,
      "mainNetInRatio": 11.28
    },
    {
      "code": "BK1651",
      "name": "显示技术",
      "change": -0.99,
      "mainNetIn": 2374793984,
      "mainNetInRatio": 4.04
    },
    {
      "code": "BK0711",
      "name": "券商概念",
      "change": -0.13,
      "mainNetIn": 2137436928,
      "mainNetInRatio": 2.83
    },
    {
      "code": "BK1142",
      "name": "裸眼3D",
      "change": -0.58,
      "mainNetIn": 1887234384,
      "mainNetInRatio": 10.82
    },
    {
      "code": "BK0948",
      "name": "MicroLED",
      "change": -0.85,
      "mainNetIn": 1874724096,
      "mainNetInRatio": 2.92
    },
    {
      "code": "BK1089",
      "name": "汽车热管理",
      "change": -1.86,
      "mainNetIn": 1812054272,
      "mainNetInRatio": 2.71
    },
    {
      "code": "BK0947",
      "name": "屏下摄像",
      "change": 1.53,
      "mainNetIn": 1483487744,
      "mainNetInRatio": 5.83
    },
    {
      "code": "BK1102",
      "name": "空气能热泵",
      "change": -2.74,
      "mainNetIn": 1205272576,
      "mainNetInRatio": 3.15
    },
    {
      "code": "BK0622",
      "name": "地热能",
      "change": -3.31,
      "mainNetIn": 1057995104,
      "mainNetInRatio": 10
    },
    {
      "code": "BK1106",
      "name": "创新药",
      "change": -0.88,
      "mainNetIn": 883302144,
      "mainNetInRatio": 1.42
    },
    {
      "code": "BK1000",
      "name": "宁组合",
      "change": -0.41,
      "mainNetIn": 882776320,
      "mainNetInRatio": 0.74
    },
    {
      "code": "BK1100",
      "name": "减速器",
      "change": 0.02,
      "mainNetIn": 851650816,
      "mainNetInRatio": 1.12
    },
    {
      "code": "BK1125",
      "name": "电子后视镜",
      "change": -0.29,
      "mainNetIn": 754838976,
      "mainNetInRatio": 3.59
    },
    {
      "code": "BK0899",
      "name": "CRO",
      "change": -0.68,
      "mainNetIn": 699426512,
      "mainNetInRatio": 3.63
    },
    {
      "code": "BK0498",
      "name": "AB股",
      "change": -1.81,
      "mainNetIn": 626849552,
      "mainNetInRatio": 2.77
    },
    {
      "code": "BK1029",
      "name": "汽车整车",
      "change": -0.36,
      "mainNetIn": 618955328,
      "mainNetInRatio": 3.24
    },
    {
      "code": "BK1190",
      "name": "虚拟机器人",
      "change": -2.58,
      "mainNetIn": 584576256,
      "mainNetInRatio": 1.4
    },
    {
      "code": "BK1107",
      "name": "科创板做市商",
      "change": -0.15,
      "mainNetIn": 538743552,
      "mainNetInRatio": 2.39
    }
  ],
  "stockInTop": [
    {
      "code": "002281",
      "name": "光迅科技",
      "price": 217.3,
      "change": -8.08,
      "mainNetIn": -3428298416,
      "mainNetInRatio": -17.18
    },
    {
      "code": "002384",
      "name": "东山精密",
      "price": 206.97,
      "change": -7.19,
      "mainNetIn": -2753590528,
      "mainNetInRatio": -14.21
    },
    {
      "code": "603986",
      "name": "兆易创新",
      "price": 431.9,
      "change": -2.95,
      "mainNetIn": -2417047040,
      "mainNetInRatio": -8.57
    },
    {
      "code": "300308",
      "name": "中际旭创",
      "price": 993.34,
      "change": -4.21,
      "mainNetIn": -2320614912,
      "mainNetInRatio": -9.51
    },
    {
      "code": "000988",
      "name": "华工科技",
      "price": 153.96,
      "change": -5.79,
      "mainNetIn": -2181170176,
      "mainNetInRatio": -11.29
    },
    {
      "code": "300394",
      "name": "天孚通信",
      "price": 337.21,
      "change": -6.07,
      "mainNetIn": -2155544736,
      "mainNetInRatio": -14.6
    },
    {
      "code": "600487",
      "name": "亨通光电",
      "price": 69.9,
      "change": -7.76,
      "mainNetIn": -2013911232,
      "mainNetInRatio": -17.03
    },
    {
      "code": "600522",
      "name": "中天科技",
      "price": 41.9,
      "change": -7.73,
      "mainNetIn": -1977235936,
      "mainNetInRatio": -14.73
    },
    {
      "code": "002475",
      "name": "立讯精密",
      "price": 67.87,
      "change": -3.14,
      "mainNetIn": -1876851520,
      "mainNetInRatio": -13.6
    },
    {
      "code": "688981",
      "name": "中芯国际",
      "price": 127.22,
      "change": -4.92,
      "mainNetIn": -1819511552,
      "mainNetInRatio": -8.83
    }
  ],
  "stockOutTop": [
    {
      "code": "002050",
      "name": "三花智控",
      "price": 52.83,
      "change": 4.51,
      "mainNetIn": 2034795648,
      "mainNetInRatio": 12.54
    },
    {
      "code": "000725",
      "name": "京东方Ａ",
      "price": 4.69,
      "change": 10.09,
      "mainNetIn": 1477258424,
      "mainNetInRatio": 30.4
    },
    {
      "code": "001896",
      "name": "豫能控股",
      "price": 16.37,
      "change": 10.01,
      "mainNetIn": 1311879776,
      "mainNetInRatio": 28.02
    },
    {
      "code": "000100",
      "name": "TCL科技",
      "price": 4.37,
      "change": 3.31,
      "mainNetIn": 984687232,
      "mainNetInRatio": 9.06
    },
    {
      "code": "601127",
      "name": "赛力斯",
      "price": 83.38,
      "change": 6.14,
      "mainNetIn": 762240560,
      "mainNetInRatio": 12.81
    },
    {
      "code": "688008",
      "name": "澜起科技",
      "price": 262.17,
      "change": 1.89,
      "mainNetIn": 713547776,
      "mainNetInRatio": 2.33
    },
    {
      "code": "300059",
      "name": "东方财富",
      "price": 19.98,
      "change": 1.58,
      "mainNetIn": 670158272,
      "mainNetInRatio": 4.51
    },
    {
      "code": "002371",
      "name": "北方华创",
      "price": 662.99,
      "change": 1.07,
      "mainNetIn": 623098624,
      "mainNetInRatio": 3.9
    },
    {
      "code": "600707",
      "name": "彩虹股份",
      "price": 11.42,
      "change": 9.91,
      "mainNetIn": 599388816,
      "mainNetInRatio": 27.16
    },
    {
      "code": "002920",
      "name": "德赛西威",
      "price": 106.12,
      "change": 10,
      "mainNetIn": 594361504,
      "mainNetInRatio": 17.83
    }
  ],
  "summary": "【资金涌入最多板块】\n1. 汽车：主力净流入 36.29 亿\n2. 面板：主力净流入 36.09 亿\n3. 汽车零部件：主力净流入 32.04 亿\n4. 家电零部件Ⅲ：主力净流入 20.98 亿\n5. 家电零部件Ⅱ：主力净流入 20.98 亿"
}